spine_asset/__init__.py
spine_asset/utils/__init__.py
spine_asset/utils/SkeletonBinaryReader.py
spine_asset/utils/SkeletonJsonReader.py
spine_asset/v38/__init__.py
spine_asset/v38/Animation.py
spine_asset/v38/AtlasFile.py
spine_asset/v38/attachments/__init__.py
spine_asset/v38/attachments/Attachment.py
spine_asset/v38/attachments/BoundingBoxAttachment.py
spine_asset/v38/attachments/ClippingAttachment.py
spine_asset/v38/attachments/MeshAttachment.py
spine_asset/v38/attachments/PathAttachment.py
spine_asset/v38/attachments/PointAttachment.py
spine_asset/v38/attachments/RegionAttachment.py
spine_asset/v38/attachments/VertexAttachment.py
spine_asset/v38/BoneData.py
spine_asset/v38/ConstraintData.py
spine_asset/v38/Enums.py
spine_asset/v38/Event.py
spine_asset/v38/EventData.py
spine_asset/v38/IkConstraintData.py
spine_asset/v38/LinkedMesh.py
spine_asset/v38/PathConstraintData.py
spine_asset/v38/SkeletonBinary.py
spine_asset/v38/SkeletonData.py
spine_asset/v38/SkeletonJson.py
spine_asset/v38/Skin.py
spine_asset/v38/SlotData.py
spine_asset/v38/timelines/__init__.py
spine_asset/v38/timelines/AttachmentTimeline.py
spine_asset/v38/timelines/ColorTimeline.py
spine_asset/v38/timelines/CurveTimeline.py
spine_asset/v38/timelines/DeformTimeline.py
spine_asset/v38/timelines/DrawOrderTimeline.py
spine_asset/v38/timelines/EventTimeline.py
spine_asset/v38/timelines/IkConstraintTimeline.py
spine_asset/v38/timelines/PathConstraintMixTimeline.py
spine_asset/v38/timelines/PathConstraintPositionTimeline.py
spine_asset/v38/timelines/PathConstraintSpacingTimeline.py
spine_asset/v38/timelines/RotateTimeline.py
spine_asset/v38/timelines/ScaleTimeline.py
spine_asset/v38/timelines/ShearTimeline.py
spine_asset/v38/timelines/Timeline.py
spine_asset/v38/timelines/TransformConstraintTimeline.py
spine_asset/v38/timelines/TranslateTimeline.py
spine_asset/v38/timelines/TwoColorTimeline.py
spine_asset/v38/TransformConstraintData.py
spine_asset-1.1.1.dist-info/LICENSE
spine_asset-1.1.1.dist-info/METADATA
spine_asset-1.1.1.dist-info/WHEEL
spine_asset-1.1.1.dist-info/RECORD
