Metadata-Version: 2.3
Name: Spine-Asset
Version: 1.1.1
Summary: Spine Animation Asset Parser Library
License: MIT
Author: Harry Huang
Author-email: harryhuang2652@qq.com
Requires-Python: >=3.9,<4
Classifier: Programming Language :: Python :: 3
Classifier: License :: OSI Approved :: MIT License
Classifier: Operating System :: OS Independent
